mcp_knowledge_search/__init__.py
mcp_knowledge_search/client.py
mcp_knowledge_search/server.py
mcp_knowledge_search-0.1.0.dist-info/METADATA
mcp_knowledge_search-0.1.0.dist-info/WHEEL
mcp_knowledge_search-0.1.0.dist-info/entry_points.txt
mcp_knowledge_search-0.1.0.dist-info/RECORD
