Metadata-Version: 2.4
Name: mcp-knowledge-search
Version: 0.1.0
Summary: MCP文档查询助手
Requires-Python: >=3.12
Requires-Dist: dotenv>=0.9.9
Requires-Dist: fastmcp>=2.3.4
Requires-Dist: httpx>=0.28.1
Requires-Dist: openai>=1.79.0
